{
  "id": "scf/overview/overview_about",
  "title": "About",
  "description": "SCF is a simple and easy to use Combat Framework that lets you setup combat for your characters from scratch in no time at all. In total there are 9 separate modular systems (actor components) in one plugin:",
  "source": "@site/docs/scf/overview/overview_about.md",
  "sourceDirName": "scf/overview",
  "slug": "/",
  "permalink": "/TeamSomber.github.io/",
  "draft": false,
  "unlisted": false,
  "tags": [],
  "version": "current",
  "sidebarPosition": 1,
  "frontMatter": {
    "id": "overview_about",
    "title": "About",
    "sidebar_position": 1,
    "slug": "/"
  },
  "sidebar": "tutorialSidebar",
  "next": {
    "title": "Installation",
    "permalink": "/TeamSomber.github.io/scf/overview/installation"
  }
}